MANIFEST.in
README.rst
setup.py
cs/__init__.py
cs.editablefooter.egg-info/PKG-INFO
cs.editablefooter.egg-info/SOURCES.txt
cs.editablefooter.egg-info/dependency_links.txt
cs.editablefooter.egg-info/entry_points.txt
cs.editablefooter.egg-info/namespace_packages.txt
cs.editablefooter.egg-info/not-zip-safe
cs.editablefooter.egg-info/requires.txt
cs.editablefooter.egg-info/top_level.txt
cs/editablefooter/__init__.py
cs/editablefooter/configure.zcml
cs/editablefooter/footer.pt
cs/editablefooter/footer.py
cs/editablefooter/interfaces.py
cs/editablefooter/permissions.zcml
cs/editablefooter/profiles.zcml
cs/editablefooter/rebuild_i18n.sh
cs/editablefooter/tests.py
cs/editablefooter/upgrades.py
cs/editablefooter/locales/cs.editablefooter-manual.pot
cs/editablefooter/locales/cs.editablefooter.pot
cs/editablefooter/locales/plone.pot
cs/editablefooter/locales/es/LC_MESSAGES/cs.editablefooter.po
cs/editablefooter/locales/es/LC_MESSAGES/plone.po
cs/editablefooter/locales/eu/LC_MESSAGES/cs.editablefooter.po
cs/editablefooter/locales/eu/LC_MESSAGES/plone.po
cs/editablefooter/profiles/default/browserlayer.xml
cs/editablefooter/profiles/default/controlpanel.xml
cs/editablefooter/profiles/default/metadata.xml
cs/editablefooter/profiles/default/propertiestool.xml
cs/editablefooter/profiles/default/rolemap.xml
cs/editablefooter/profiles/default/viewlets.xml
docs/HISTORY.txt
docs/INSTALL.txt
docs/LICENSE.GPL
docs/LICENSE.txt