Metadata-Version: 1.1
Name: cs.editablefooter
Version: 2.1.1
Summary: A simple package providing a editable footer for Plone
Home-page: http://github.com/codesyntax/cs.editablefooter
Author: Mikel Larreategi
Author-email: mlarreategi@codesyntax.com
License: GPL
Keywords: plone viewlet footer
Platform: UNKNOWN
Classifier: Framework :: Plone
Classifier: Programming Language :: Python
